moonlight/__init__.py
moonlight/src/agent/__init__.py
moonlight/src/agent/base.py
moonlight/src/agent/history.py
moonlight/src/agent/main.py
moonlight/src/helpers/__init__.py
moonlight/src/helpers/model_converter.py
moonlight/src/provider/__init__.py
moonlight/src/provider/completion.py
moonlight/src/provider/main.py
moonlight/src/tests/test_agent_history.py
moonlight/src/tests/test_model_converter.py
moonlight/src/tests/test_providers.py
moonlight_ai-0.2.7.dist-info/licenses/LICENSE
moonlight_ai-0.2.7.dist-info/METADATA
moonlight_ai-0.2.7.dist-info/WHEEL
moonlight_ai-0.2.7.dist-info/top_level.txt
moonlight_ai-0.2.7.dist-info/RECORD
