Metadata-Version: 2.4
Name: moonlight-ai
Version: 0.2.7
Summary: Lightweight AI Agents SDK for building intelligent automation systems
Home-page: https://github.com/ecstra/moonlight
Author: ecstra
Author-email: ecstra <themythbustertmb@gmail.com>
License: MIT
Project-URL: Homepage, https://github.com/ecstra/moonlight
Project-URL: Repository, https://github.com/ecstra/moonlight
Project-URL: Documentation, https://github.com/ecstra/moonlight#readme
Project-URL: Bug Tracker, https://github.com/ecstra/moonlight/issues
Keywords: ai,agents,automation,sdk,llm,minimal,artificial-intelligence,openai,deepseek,groq,openrouter,google,together,hugging-face
Classifier: Development Status :: 4 - Beta
Classifier: Intended Audience :: Developers
Classifier: License :: OSI Approved :: MIT License
Classifier: Operating System :: OS Independent
Classifier: Programming Language :: Python :: 3
Classifier: Programming Language :: Python :: 3.9
Classifier: Programming Language :: Python :: 3.10
Classifier: Programming Language :: Python :: 3.11
Classifier: Programming Language :: Python :: 3.12
Classifier: Programming Language :: Python :: 3.13
Classifier: Programming Language :: Python :: 3.14
Classifier: Topic :: Software Development :: Libraries :: Python Modules
Classifier: Topic :: Scientific/Engineering :: Artificial Intelligence
Requires-Python: >=3.9
License-File: LICENSE
Requires-Dist: httpx==0.28.1
Requires-Dist: pydantic==2.12.5
Requires-Dist: requests==2.32.5
Dynamic: author
Dynamic: home-page
Dynamic: license-file
Dynamic: requires-python
